wsl_path_converter/__init__.py
wsl_path_converter/main.py
wsl_path_converter-0.3.1.dist-info/LICENSE.txt
wsl_path_converter-0.3.1.dist-info/METADATA
wsl_path_converter-0.3.1.dist-info/WHEEL
wsl_path_converter-0.3.1.dist-info/entry_points.txt
wsl_path_converter-0.3.1.dist-info/top_level.txt
wsl_path_converter-0.3.1.dist-info/RECORD
