Metadata-Version: 2.1
Name: wsl-path-converter
Version: 0.3.1
Summary: Convert between Linux and Windows path in WSL
Home-page: https://github.com/lamyj/wsl-path-converter
Author: Julien Lamy
Author-email: lamy@unistra.fr
License: MIT
Keywords: wsl,windows,linux,path
Platform: UNKNOWN
Classifier: Development Status :: 5 - Production/Stable
Classifier: Environment :: Console
Classifier: Intended Audience :: End Users/Desktop
Classifier: Intended Audience :: Information Technology
Classifier: Intended Audience :: Science/Research
Classifier: Intended Audience :: System Administrators
Classifier: Topic :: Communications :: File Sharing
Classifier: Topic :: System :: Archiving :: Mirroring
Classifier: License :: OSI Approved :: MIT License
Classifier: Operating System :: Microsoft :: Windows
Classifier: Programming Language :: Python :: 2
Classifier: Programming Language :: Python :: 3
Classifier: Topic :: System :: Filesystems
